recommendation/__init__.py
recommendation/tools/__init__.py
recommendation/tools/recommendation_api_tool.py
recommendation/tools/utils.py
recommendation/yamls/recommendation_api_tool.yaml
tests/__init__.py
tests/test_recommendation_api_tool.py
recommendation_intelligence_flow-0.0.3.dist-info/METADATA
recommendation_intelligence_flow-0.0.3.dist-info/WHEEL
recommendation_intelligence_flow-0.0.3.dist-info/entry_points.txt
recommendation_intelligence_flow-0.0.3.dist-info/top_level.txt
recommendation_intelligence_flow-0.0.3.dist-info/RECORD
