Metadata-Version: 2.1
Name: recommendation_intelligence_flow
Version: 0.0.3
Summary: This is Recommendation Intelligence prompt flow
